static_data_functions/__init__.py
static_data_functions/importer.py
static_data_functions-1.0.0.dist-info/METADATA
static_data_functions-1.0.0.dist-info/WHEEL
static_data_functions-1.0.0.dist-info/top_level.txt
static_data_functions-1.0.0.dist-info/RECORD
